{"note":"This file is an internal implementation detail to speed up HTML report generation. Its format can change at any time. You might be looking for the JSON report: https://coverage.rtfd.io/cmd.html#cmd-json","format":2,"version":"7.4.4","globals":"00ccaa40dafb2fc1e49b15f0f2edd96b","files":{"app_py":{"hash":"ba4016e9711e78f70c822a2e8a9616b2","index":{"nums":[0,1,17,0,0,0,0,0],"html_filename":"app_py.html","relative_filename":"app.py"}},"unit_py":{"hash":"a6bc88a7f6dea65423190d7c3d6d1dbb","index":{"nums":[0,1,28,0,1,0,0,0],"html_filename":"unit_py.html","relative_filename":"unit.py"}}}}